{
  "name": "bit-adder-input-neurons-0+1",
  "neurons": [
    {
      "id": 0,
      "label": "n2-Tx5pOCJeb",
      "position": {
        "x": 464,
        "y": 306
      },
      "rules": [
        {
          "regex": "a",
          "consumed": 1,
          "produced": 1,
          "delay": 0
        },
        {
          "regex": "2a",
          "consumed": 1,
          "produced": 0,
          "delay": 0
        },
        {
          "regex": "3a",
          "consumed": 2,
          "produced": 1,
          "delay": 0
        }
      ],
      "spikes": 0,
      "downtime": 0
    },
    {
      "id": 1,
      "label": "n0-n5HhlTm3T",
      "position": {
        "x": 190,
        "y": 173
      },
      "rules": [],
      "spikes": 0,
      "downtime": 0
    },
    {
      "id": 2,
      "label": "n1-DumthuGnF",
      "position": {
        "x": 164,
        "y": 417
      },
      "rules": [],
      "spikes": 0,
      "downtime": 0
    },
    {
      "id": 3,
      "label": "out1-jhzeGGrV_",
      "position": {
        "x": 632,
        "y": 304
      },
      "rules": [],
      "spikes": 0,
      "downtime": 0
    }
  ],
  "synapses": [
    {
      "from": 0,
      "to": 3,
      "weight": 1
    },
    {
      "from": 1,
      "to": 0,
      "weight": 1
    },
    {
      "from": 2,
      "to": 0,
      "weight": 1
    }
  ],
  "inputNeurons": [
    {
      "id": 1,
      "spikeTimes": []
    },
    {
      "id": 2,
      "spikeTimes": [
        0
      ]
    }
  ],
  "outputNeurons": [
    {
      "id": 3,
      "spikeTimes": []
    }
  ]
}